[
  {
    "Id": 1,
    "Name": "Car Fund",
    "TargetAmount": 5000.0,
    "CurrentAmount": 2500.0,
    "TargetDate": "2024-12-31T00:00:00"
  },
  {
    "Id": 2,
    "Name": "Vacation",
    "TargetAmount": 3000.0,
    "CurrentAmount": 1000.0,
    "TargetDate": "2025-06-15T00:00:00"
  },
  {
    "Id": 3,
    "Name": "Emergency Fund",
    "TargetAmount": 10000.0,
    "CurrentAmount": 7000.0,
    "TargetDate": "2025-01-01T00:00:00"
  },
  {
    "Id": 4,
    "Name": "House Down Payment",
    "TargetAmount": 20000.0,
    "CurrentAmount": 8000.0,
    "TargetDate": "2026-05-20T00:00:00"
  },
  {
    "Id": 5,
    "Name": "Education",
    "TargetAmount": 15000.0,
    "CurrentAmount": 5000.0,
    "TargetDate": "2025-09-01T00:00:00"
  },
  {
    "Id": 6,
    "Name": "Wedding",
    "TargetAmount": 12000.0,
    "CurrentAmount": 6000.0,
    "TargetDate": "2025-11-25T00:00:00"
  },
  {
    "Id": 7,
    "Name": "New Laptop",
    "TargetAmount": 1500.0,
    "CurrentAmount": 800.0,
    "TargetDate": "2024-08-01T00:00:00"
  },
  {
    "Id": 8,
    "Name": "Investment Fund",
    "TargetAmount": 10000.0,
    "CurrentAmount": 3000.0,
    "TargetDate": "2025-12-31T00:00:00"
  },
  {
    "Id": 9,
    "Name": "Home Renovation",
    "TargetAmount": 8000.0,
    "CurrentAmount": 4000.0,
    "TargetDate": "2024-12-15T00:00:00"
  },
  {
    "Id": 10,
    "Name": "Charity Fund",
    "TargetAmount": 5000.0,
    "CurrentAmount": 2500.0,
    "TargetDate": "2025-07-20T00:00:00"
  }
]
